libenv/__init__.py
libenv/artifacts.py
libenv/config.py
libenv/console.py
libenv/envtype.py
libenv/libenv.py
libenv/lmod.py
libenv/py.typed
libenv/spec.py
libenv/types/__init__.py
libenv/types/autotools.py
libenv/types/cmake.py
libenv/types/depends.py
libenv/types/julia.py
libenv/types/module.py
libenv/types/script.py
libenv/types/spack.py
libenv/types/var.py
libenv/types/venv.py
libenv-1.2.0.dist-info/METADATA
libenv-1.2.0.dist-info/WHEEL
libenv-1.2.0.dist-info/entry_points.txt
libenv-1.2.0.dist-info/RECORD
