Metadata-Version: 2.3
Name: libenv
Version: 1.2.0
Summary: Declare an Environment
License: BSD-3-Clause
Author: David M. Rogers
Author-email: predictivestatmech@gmail.com
Requires-Python: >=3.9,<4.0
Classifier: License :: OSI Approved :: BSD License
Classifier: Programming Language :: Python :: 3
Classifier: Programming Language :: Python :: 3.9
Classifier: Programming Language :: Python :: 3.10
Classifier: Programming Language :: Python :: 3.11
Classifier: Programming Language :: Python :: 3.12
Classifier: Programming Language :: Python :: 3.13
Requires-Dist: PyYAML (>=6.0.1,<7.0)
Requires-Dist: aurl-aurl (>=2.5.0)
Requires-Dist: importlib-metadata (>=6.8.0)
Requires-Dist: pydantic (>=2.1.1,<3.0)
Requires-Dist: rich (>=14.0)
Requires-Dist: typer (>=0.9.0)
Project-URL: Repository, https://gitlab.com/frobnitzem/libenv
